environment_provider/__init__.py
environment_provider/environment_provider.py
environment_provider/lib/__init__.py
environment_provider/lib/celery.py
environment_provider/lib/config.py
environment_provider/lib/database.py
environment_provider/lib/encrypt.py
environment_provider/lib/graphql.py
environment_provider/lib/join.py
environment_provider/lib/json_dumps.py
environment_provider/lib/log_area.py
environment_provider/lib/registry.py
environment_provider/lib/test_suite.py
environment_provider/lib/uuid_generate.py
environment_provider/splitter/__init__.py
environment_provider/splitter/split.py
environment_provider_api/.gitignore
environment_provider_api/__init__.py
environment_provider_api/webserver.py
environment_provider_api/backend/__init__.py
environment_provider_api/backend/common.py
environment_provider_api/backend/configure.py
environment_provider_api/backend/environment.py
environment_provider_api/backend/register.py
environment_provider_api/middleware/__init__.py
environment_provider_api/middleware/json_translator.py
environment_provider_api/middleware/require_json.py
execution_space_provider/__init__.py
execution_space_provider/exceptions.py
execution_space_provider/execution_space.py
execution_space_provider/execution_space_provider.py
execution_space_provider/schemas/external_schema.json
execution_space_provider/schemas/jsontas_schema.json
execution_space_provider/utilities/__init__.py
execution_space_provider/utilities/checkin.py
execution_space_provider/utilities/checkout.py
execution_space_provider/utilities/external_provider.py
execution_space_provider/utilities/instructions.py
execution_space_provider/utilities/jsontas_provider.py
execution_space_provider/utilities/list.py
iut_provider/__init__.py
iut_provider/exceptions.py
iut_provider/iut.py
iut_provider/iut_provider.py
iut_provider/schemas/external_schema.json
iut_provider/schemas/jsontas_schema.json
iut_provider/utilities/__init__.py
iut_provider/utilities/checkin.py
environment_provider-3.2.1.dist-info/AUTHORS.rst
environment_provider-3.2.1.dist-info/LICENSE.txt
environment_provider-3.2.1.dist-info/METADATA
environment_provider-3.2.1.dist-info/WHEEL
environment_provider-3.2.1.dist-info/top_level.txt
environment_provider-3.2.1.dist-info/RECORD
