Metadata-Version: 2.1
Name: environment_provider
Version: 3.2.1
Summary: Environment provider for ETOS.
Home-page: https://github.com/eiffel-community/etos-environment-provider
Author: Tobias Persson
Author-email: tobias.persson@axis.com
License: Apache License, Version 2.0
Project-URL: Documentation, https://etos.readthedocs.io/
Platform: Linux
Classifier: Development Status :: 4 - Beta
Classifier: Programming Language :: Python :: 3 :: Only
Classifier: Programming Language :: Python :: 3.9
Classifier: License :: OSI Approved :: Apache Software License
Requires-Python: >=3.8
License-File: LICENSE.txt
License-File: AUTHORS.rst
Requires-Dist: eventlet ~=0.33
Requires-Dist: celery ~=5.3
Requires-Dist: cryptography <43.0.0,>=42.0.4
Requires-Dist: gevent ~=23.7
Requires-Dist: gunicorn ~=19.9
Requires-Dist: falcon ~=3.1
Requires-Dist: jsontas ~=1.3
Requires-Dist: packageurl-python ~=0.11
Requires-Dist: etcd3gw ~=2.3
Requires-Dist: etos-lib ==4.0.0
Provides-Extra: testing
Requires-Dist: pytest ; extra == 'testing'
Requires-Dist: pytest-cov ; extra == 'testing'
